<?xml version="1.0" encoding="UTF-8" ?>
<Dialog close_offset="5,5" flag="title" frame="0,262,135,241" h_pos_align="left" last_modified="2020-09-07 20:08:54" name="party_sub_dialog" preset="v4_force_sep" title_frame="3,3,96,14" title_height="17" type="dlg_party_sub" v_pos_align="top">
	<Widget drag_type="30" frame="4,-2,126,36" name="ctn_member1" preset="v4_force_sep_ctn" type="containerex">
		<Widget frame="34,15,83,7" name="hp_bg" preset="v4_party_hp_gauge_bg" show_value="False" skin_extend="True" stage="2" state_depended="True" type="gauge" value_type="percent">
		</Widget>
		<Widget frame="34,15,83,7" name="hp" num_type="micro" preset="v4_party_hp_gauge" show_value="False" skin_extend="True" small_number="True" stage="2" state_depended="True" type="gauge" value_type="number">
		</Widget>
		<Widget frame="34,25,83,7" name="mp_bg" preset="v4_party_mp_gauge_bg" skin_extend="True" type="gauge">
		</Widget>
		<Widget frame="34,25,83,7" name="mp" num_type="micro" preset="v4_party_mp_gauge" skin_extend="True" small_number="True" type="gauge" value_type="number">
		</Widget>
		<Widget frame="6,10,19,19" name="emblem" preset="v4_class_icon" type="image">
		</Widget>
		<Widget flag="truncate" frame="34,0,92,13" name="title" text_shade="True" type="static">
		</Widget>
		<Widget flag="visible;not_active" frame="0,5,31,31" gauge_flags="time" name="fly_gauge" preset="v4_force_fly_gauge" type="flygauge">
		</Widget>
	</Widget>
	<Widget drag_type="30" frame="4,35,126,36" name="ctn_member2" preset="v4_force_sep_ctn" type="containerex">
		<Widget frame="34,15,83,7" name="hp_bg" preset="v4_party_hp_gauge_bg" show_value="False" skin_extend="True" stage="2" state_depended="True" type="gauge" value_type="percent">
		</Widget>
		<Widget frame="34,15,83,7" name="hp" num_type="micro" preset="v4_party_hp_gauge" show_value="False" skin_extend="True" small_number="True" stage="2" state_depended="True" type="gauge" value_type="number">
		</Widget>
		<Widget frame="34,25,83,7" name="mp_bg" preset="v4_party_mp_gauge_bg" skin_extend="True" type="gauge">
		</Widget>
		<Widget frame="34,25,83,7" name="mp" num_type="micro" preset="v4_party_mp_gauge" skin_extend="True" small_number="True" type="gauge" value_type="number">
		</Widget>
		<Widget frame="6,10,19,19" name="emblem" preset="v4_class_icon" type="image">
		</Widget>
		<Widget flag="truncate" frame="34,0,92,13" name="title" text_shade="True" type="static">
		</Widget>
		<Widget flag="visible;not_active" frame="0,5,31,31" gauge_flags="time" name="fly_gauge" preset="v4_force_fly_gauge" type="flygauge">
		</Widget>
	</Widget>
	<Widget drag_type="30" frame="4,72,126,36" name="ctn_member3" preset="v4_force_sep_ctn" type="containerex">
		<Widget frame="34,15,83,7" name="hp_bg" preset="v4_party_hp_gauge_bg" show_value="False" skin_extend="True" stage="2" state_depended="True" type="gauge" value_type="percent">
		</Widget>
		<Widget frame="34,15,83,7" name="hp" num_type="micro" preset="v4_party_hp_gauge" show_value="False" skin_extend="True" small_number="True" stage="2" state_depended="True" type="gauge" value_type="number">
		</Widget>
		<Widget frame="34,25,83,7" name="mp_bg" preset="v4_party_mp_gauge_bg" skin_extend="True" type="gauge">
		</Widget>
		<Widget frame="34,25,83,7" name="mp" num_type="micro" preset="v4_party_mp_gauge" skin_extend="True" small_number="True" type="gauge" value_type="number">
		</Widget>
		<Widget frame="6,10,19,19" name="emblem" preset="v4_class_icon" type="image">
		</Widget>
		<Widget flag="truncate" frame="34,0,92,13" name="title" text_shade="True" type="static">
		</Widget>
		<Widget flag="visible;not_active" frame="0,5,31,31" gauge_flags="time" name="fly_gauge" preset="v4_force_fly_gauge" type="flygauge">
		</Widget>
	</Widget>
	<Widget drag_type="30" frame="4,109,126,36" name="ctn_member4" preset="v4_force_sep_ctn" type="containerex">
		<Widget frame="34,15,83,7" name="hp_bg" preset="v4_party_hp_gauge_bg" show_value="False" skin_extend="True" stage="2" state_depended="True" type="gauge" value_type="percent">
		</Widget>
		<Widget frame="34,15,83,7" name="hp" num_type="micro" preset="v4_party_hp_gauge" show_value="False" skin_extend="True" small_number="True" stage="2" state_depended="True" type="gauge" value_type="number">
		</Widget>
		<Widget frame="34,25,83,7" name="mp_bg" preset="v4_party_mp_gauge_bg" skin_extend="True" type="gauge">
		</Widget>
		<Widget frame="34,25,83,7" name="mp" num_type="micro" preset="v4_party_mp_gauge" skin_extend="True" small_number="True" type="gauge" value_type="number">
		</Widget>
		<Widget frame="6,10,19,19" name="emblem" preset="v4_class_icon" type="image">
		</Widget>
		<Widget flag="truncate" frame="34,0,92,13" name="title" text_shade="True" type="static">
		</Widget>
		<Widget flag="visible;not_active" frame="0,5,31,31" gauge_flags="time" name="fly_gauge" preset="v4_force_fly_gauge" type="flygauge">
		</Widget>
	</Widget>
	<Widget drag_type="30" frame="4,146,126,36" name="ctn_member5" preset="v4_force_sep_ctn" type="containerex">
		<Widget frame="34,15,83,7" name="hp_bg" preset="v4_party_hp_gauge_bg" show_value="False" skin_extend="True" stage="2" state_depended="True" type="gauge" value_type="percent">
		</Widget>
		<Widget frame="34,15,83,7" name="hp" num_type="micro" preset="v4_party_hp_gauge" show_value="False" skin_extend="True" small_number="True" stage="2" state_depended="True" type="gauge" value_type="number">
		</Widget>
		<Widget frame="34,25,83,7" name="mp_bg" preset="v4_party_mp_gauge_bg" skin_extend="True" type="gauge">
		</Widget>
		<Widget frame="34,25,83,7" name="mp" num_type="micro" preset="v4_party_mp_gauge" skin_extend="True" small_number="True" type="gauge" value_type="number">
		</Widget>
		<Widget frame="6,10,19,19" name="emblem" preset="v4_class_icon" type="image">
		</Widget>
		<Widget flag="truncate" frame="34,0,92,13" name="title" text_shade="True" type="static">
		</Widget>
		<Widget flag="visible;not_active" frame="0,5,31,31" gauge_flags="time" name="fly_gauge" preset="v4_force_fly_gauge" type="flygauge">
		</Widget>
	</Widget>
	<Widget drag_type="30" frame="4,183,126,36" name="ctn_member6" preset="v4_force_sep_ctn" type="containerex">
		<Widget frame="34,15,83,7" name="hp_bg" preset="v4_party_hp_gauge_bg" show_value="False" skin_extend="True" stage="2" state_depended="True" type="gauge" value_type="percent">
		</Widget>
		<Widget frame="34,15,83,7" name="hp" num_type="micro" preset="v4_party_hp_gauge" show_value="False" skin_extend="True" small_number="True" stage="2" state_depended="True" type="gauge" value_type="number">
		</Widget>
		<Widget frame="34,25,83,7" name="mp_bg" preset="v4_party_mp_gauge_bg" skin_extend="True" type="gauge">
		</Widget>
		<Widget frame="34,25,83,7" name="mp" num_type="micro" preset="v4_party_mp_gauge" skin_extend="True" small_number="True" type="gauge" value_type="number">
		</Widget>
		<Widget frame="6,10,19,19" name="emblem" preset="v4_class_icon" type="image">
		</Widget>
		<Widget flag="truncate" frame="34,0,92,13" name="title" text_shade="True" type="static">
		</Widget>
		<Widget flag="visible;not_active" frame="0,5,31,31" gauge_flags="time" name="fly_gauge" preset="v4_force_fly_gauge" type="flygauge">
		</Widget>
	</Widget>
	<Widget flag="not_visible" frame="137,-14,134,39" name="select" type="image">
		<Skin name="v4_force_sep_over">
		</Skin>
	</Widget>
</Dialog>
