<?xml version="1.0" encoding="UTF-8" ?>
<GraphicChars>
	<char>money</char>
	<char>higher</char>
	<char>lower</char>
	<char>high</char>
	<char>low</char>
	<char>warn</char>
	<char>target_left</char>
	<char>target_right</char>
	<char>target_left_a</char>
	<char>target_right_a</char>
	<char>abyss_point</char>
	<char>kill_point</char>
	<char>same</char>
	<char>pet_attack</char>
	<char>pet_move</char>
	<char>pet_rest</char>
	<char>pet_unsummon</char>
	<char>group_1</char>
	<char>group_2</char>
	<char>group_3</char>
	<char>group_4</char>
	<char>sign_1</char>
	<char>sign_2</char>
	<char>sign_3</char>
	<char>sign_4</char>
	<char>sign_15</char>
	<char>sign_16</char>
	<char>sign_7</char>
	<char>sign_8</char>
	<char>sign_9</char>
	<char>sign_10</char>
	<char>sign_11</char>
	<char>sign_12</char>
	<char>sign_13</char>
	<char>sign_14</char>
	<char>medal_01</char>
	<char>medal_02</char>
	<char>coupon_jewel</char>
	<char coloroverlay="true">timer</char>
	<char coloroverlay="true">alarm</char>
	<char>mercenary_move</char>
	<char>mercenary_attack</char>
	<char>medal_03</char>
	<char>coin_01</char>
	<char>coin_02</char>
	<char>coin_03</char>
	<char>coin_04</char>
	<char>coin_05</char>
	<char>coin_06</char>
	<char>coin_protection</char>
	<char>coin_headquarters</char>
	<char>coin_hunters</char>
	<char>quest_givable</char>
	<char>quest_working</char>
	<char>quest_finished</char>
	<char>mission_working</char>
	<char>mission_finished</char>
	<char>event_givable</char>
	<char>event_working</char>
	<char>event_finished</char>
	<char>sign_5</char>
	<char>sign_6</char>
	<char>coin_mentor</char>
	<char>important_givable</char>
	<char>important_working</char>
	<char>important_finished</char>
	<char>wing_left</char>
	<char>wing_right</char>
	<char>event_coin_01</char>
	<char>coin_shulack</char>
	<char>coin_heart_01</char>
	<char>coin_heart_02</char>
	<char>coin_heart_03</char>
	<char>event_coin_02</char>
	<char>boss_raid_light</char>
	<char>boss_raid_dark</char>
	<char>underpass</char>
	<char>fortress</char>
	<char>fortress_pvp</char>
	<char>artifact</char>
	<char>carrier</char>
	<char>dragon</char>
	<char>light</char>
	<char>dark</char>
	<char>funcnpc_merchant</char>
	<char>funcnpc_vendor</char>
	<char>funcnpc_warehouse</char>
	<char>funcnpc_teleport</char>
	<char>funcnpc_postbox</char>
	<char>funcnpc_bindstone</char>
	<char>party</char>
	<char>force</char>
	<char>indun</char>
	<char>medal_arena_01</char>
	<char>cant_attack</char>
	<char>equipment</char>
	<char>medal_04</char>
	<char>drana_prism</char>
	<char>coin_07</char>
	<char>coin_08</char>
	<char>tower</char>
	<char>portal</char>
	<char>medal_arena_pvp_01</char>
	<char>stigma_master</char>
	<char>funcnpc_coin_merchant</char>
	<char>condition_npc</char>
	<char>same_green</char>
	<char>event_coin_04</char>
	<char>quna</char>
	<char>coin_09</char>
	<char>flag_buy_each</char>
	<char>Icon_Item_Coin_Tiamat_01</char>
	<char>icon_Classic_festival_Coin_01</char>
	<char>Icon_item_badge10</char>
	<char>Icon_item_badge11</char>
	<char>Icon_item_badge12</char>
	<char>Icon_item_badge13</char>
	<char>Icon_item_badge14</char>
	<char>Icon_item_badge15</char>
	<char>Icon_Cash_Item_Songpyeon_02</char>
	<char>icon_classic_event_coin_idpogusgame</char>
	<char>Icon_Item_Tooth01</char>
	<char>Icon_event_wday_flowerbouquet_01</char>
	<char>Icon_Lucky_Coin</char>
	<char>Icon_item_badge20</char>
</GraphicChars>
