<?xml version="1.0" encoding="UTF-8" ?>
<CutSceneText>
	<Text label="P01">You’ll find the Balaur Wardstones inside the Indratu Barracks.</Text>
	<Text label="P02">They don’t look like the natural stone pillars in the caverns there...</Text>
	<Text label="P03">they’re blue and oddly shaped.</Text>
	<Text label="P04">Destroying them will be a great blow to the Balaur,</Text>
	<Text label="P05">but you’ll still have Drafala to deal with.</Text>
	<Text label="P06">Killing him – if you can – will weaken them greatly.</Text>
</CutSceneText>
