<?xml version="1.0" encoding="UTF-8" ?>
<Dialog close_offset="4,1" close_preset="v5_close" flag="close;title" frame="300,200,340,398" last_modified="2019-07-30 17:22:00" name="idscore_dmg_dialog" preset="v5_dialog2" shadow_offset="8,8" title_align="center" title_frame="3,3,334,14" title_height="25" title_offset="0,5" title_text="STR_INDUN_ACCOUNT_IDLF1_DIALOG" type="dlg_idscore_dmg">
	<Widget frame="2,0,330,119" name="over_info" type="container">
		<Widget frame="0,0,330,119" type="image">
			<Skin name="v5_indun_account_rank" state="0">
			</Skin>
		</Widget>
		<Widget font_size="64" frame="139,30,53,59" halign="center" name="rank" preset="v5_indun_rank" text_color="0.0,0.0,0.0,1.0" text_shade="True" type="static" valign="middle">
		</Widget>
		<Widget font_size="14" frame="145,3,41,18" halign="center" text="STR_INDUN_ACCOUNT_IDLF1_DIALOG__RANK" text_color="0.0,0.0,0.0,1.0" text_shade="True" type="static">
		</Widget>
	</Widget>
	<Widget column_heading="False" flag="not_active;truncate" font="idscore_default" frame="2,117,330,36" header_height="0" item_height="30" item_num="2" list_padding="15,3" name="total" text_shade="True" type="listviewex">
		<Skin name="v5_indun_account_col">
		</Skin>
		<Column align="" img_width="" sample_text="texttexttexttexttexttext" sort="" title="" width="150">
		</Column>
		<Column align="right" img_width="" sample_text="score" sort="none" title="" width="150">
		</Column>
	</Widget>
	<Widget column_heading="False" flag="not_active;truncate" font="idscore_default" frame="2,154,330,36" header_height="0" item_height="30" item_num="2" list_padding="15,3" name="remain_rank" text_shade="True" type="listviewex">
		<Skin name="v5_indun_account_box">
		</Skin>
		<Column align="" img_width="" sample_text="texttexttexttexttexttext" sort="" title="" width="150">
		</Column>
		<Column align="right" img_width="" sample_text="score" sort="none" title="" width="150">
		</Column>
	</Widget>
	<Widget column_heading="False" flag="not_active;truncate" font="idscore_default" frame="2,191,330,36" header_height="0" item_height="30" item_num="2" list_padding="15,3" name="remain_time" text_shade="True" type="listviewex">
		<Skin name="v5_indun_account_box">
		</Skin>
		<Column align="" img_width="" sample_text="texttexttexttexttexttext" sort="" title="" width="150">
		</Column>
		<Column align="right" img_width="" sample_text="score" sort="none" title="" width="150">
		</Column>
	</Widget>
	<Widget column_heading="False" flag="not_active;truncate" font="idscore_default" font_size="14" frame="2,228,330,107" header_height="0" item_height="20" item_num="5" list_padding="15,3" name="reward" text_shade="True" type="listviewex">
		<Skin name="v5_indun_account_box">
		</Skin>
		<Column align="" img_width="" sample_text="texttexttexttexttexttext" sort="" title="" width="150">
		</Column>
		<Column align="right" img_width="" sample_text="score" sort="none" title="" width="150">
		</Column>
	</Widget>
	<Widget font="ui_default" frame="250,341,82,24" name="cancel_button" preset="v5_button" text="STR_COMMON__OK" type="button" v_pos_align="bottom">
	</Widget>
	<Widget font="ui_default" frame="106,341,122,24" name="leave" preset="v5_button" text="STR_INDUN_ACCOUNT_IDLF1_DIALOG__LEAVE" type="button" v_pos_align="bottom">
	</Widget>
	<Widget flag="not_visible" frame="2,191,330,187" name="standard" type="container">
		<Skin name="v5_indun_account_box">
		</Skin>
		<Widget font="idscore_default" frame="18,6,197,17" text="STR_IDSCORE_DIALOG__RANK_STANDARD" type="static">
		</Widget>
		<Widget cell_padding="2" cell_space="0,0" column_heading="True" flag="vscroll;not_active" font="ui_list" frame="2,27,326,159" h_pos_align="proportion" header_font="v3_columnhead" header_height="24" item_height="22" item_num="5" item_width="44" list_padding="1,1" name="rank_standard" preset="v5_listview_ex" scroll_type="auto" skin_type="version5" slot_num="5" type="listviewex" v_pos_align="proportion">
			<Column align="center" img_width="" sample_text="" sort="" title="STR_IDSCORE_DIALOG__HEADER_RANK" width="59">
			</Column>
			<Column align="center" img_width="" sample_text="" sort="" title="STR_IDSCORE_DIALOG__HEADER_TOTAL_SCORE" width="140">
			</Column>
			<Column align="center" img_width="" sample_text="" sort="" title="STR_IDSCORE_DIALOG__HEADER_TIME" width="125">
			</Column>
		</Widget>
	</Widget>
</Dialog>
